<?xml version="1.0" encoding="utf-8" ?>
<dwsync>
<file name="main-responsive.css" server="C:/wamp/www/ecomer/" local="130322557740000000" remote="130322521740000000" Dst="2" />
<file name="main.css" server="C:/wamp/www/ecomer/" local="130353814620000000" remote="130353778620000000" Dst="2" />
<file name="print.css" server="C:/wamp/www/ecomer/" local="130322711520000000" remote="130322675520000000" Dst="2" />
<file name="rtl-version.css" server="C:/wamp/www/ecomer/" local="130292231380000000" remote="130292195380000000" Dst="2" />
<file name="theme_black_and_white.css" server="C:/wamp/www/ecomer/" local="130288218800000000" remote="130288182800000000" Dst="2" />
<file name="theme_dark.css" server="C:/wamp/www/ecomer/" local="130288220140000000" remote="130288184140000000" Dst="2" />
<file name="theme_green.css" server="C:/wamp/www/ecomer/" local="130288218200000000" remote="130288182200000000" Dst="2" />
<file name="theme_light.css" server="C:/wamp/www/ecomer/" local="130288216460000000" remote="130288180460000000" Dst="2" />
<file name="theme_navy.css" server="C:/wamp/www/ecomer/" local="130288218540000000" remote="130288182540000000" Dst="2" />
</dwsync>